frequency_feature_map_visualization/__init__.py
frequency_feature_map_visualization/feature_map_visualization.py
frequency_feature_map_visualization-0.6.0.dist-info/METADATA
frequency_feature_map_visualization-0.6.0.dist-info/WHEEL
frequency_feature_map_visualization-0.6.0.dist-info/top_level.txt
frequency_feature_map_visualization-0.6.0.dist-info/RECORD
